{"base":{"symbol":"LAWR.US","name":"Robot Consulting Co., Ltd. ADS","exchange":"NASDAQ","exchange_name":null,"country":"USA","region":"US","currency":"USD","status":"priced","list_date":"2025-07-10","filing_date":"2025-07-10","amended_date":"2025-07-10","deal_type":"Expected","offer_price":null,"price_low":null,"price_high":null,"shares":3750000,"last_price":null,"previous_close":null,"change_pct":null,"sector":"Industrials","industry":"Consulting Services","description":"Robot Consulting Co., Ltd.","market_cap":172350000.0,"employees":18,"web_url":"https://robotconsulting.net","logo_url":null,"tags":["Industrials","Consulting Services","Micro-cap","USA","Priced"],"prospectus_url":null},"stats":[{"label":"Symbol","value":"LAWR.US"},{"label":"Sector","value":"Industrials"},{"label":"Industry","value":"Consulting Services"},{"label":"Country","value":"USA"},{"label":"Employees","value":"18"},{"label":"Market Cap","value":"$172.35M"},{"label":"Revenue (TTM)","value":"$575.77M"},{"label":"EBITDA","value":"$-904.33M"},{"label":"Profit Margin","value":"-162.32%"},{"label":"ROE (TTM)","value":"0.00%"},{"label":"Forward P/E","value":"0.00"},{"label":"52W High","value":"$4.84"},{"label":"52W Low","value":"$1.50"},{"label":"IPO Date","value":"2025-07-17"},{"label":"Fiscal Year End","value":"March"}],"financials":{"rows":[{"label":"Revenue","period_labels":["2022","2023","2024","2025"],"values":["¥127.32M","¥83.60M","¥693.10M","¥675.56M"]},{"label":"Net Income","period_labels":["2022","2023","2024","2025"],"values":["¥-117.96M","¥-478.63M","¥-661.97M","¥-534.68M"]},{"label":"EBITDA","period_labels":["2022","2023","2024","2025"],"values":["¥-120.63M","¥-478.39M","¥-660.13M","¥-531.79M"]},{"label":"Operating Cash Flow","period_labels":["2022","2023","2024","2025"],"values":["¥-95.35M","¥-133.76M","¥-317.06M","¥-283.02M"]},{"label":"Total Assets","period_labels":["2022","2023","2024","2025"],"values":["¥334.26M","¥633.75M","¥743.54M","¥313.97M"]},{"label":"Total Equity","period_labels":["2022","2023","2024","2025"],"values":["¥302.64M","¥176.83M","¥-116.70M","¥-651.38M"]},{"label":"Net Margin","period_labels":["2022","2023","2024","2025"],"values":["-92.65%","-572.55%","-95.51%","-79.15%"]}],"fiscal_year_end":"March","reporting_currency":"JPY"},"analyst":{"rating":null,"target_price":null,"target_pct_vs_current":null,"strong_buy":0,"buy":0,"hold":0,"sell":0,"strong_sell":0},"top_holders":[],"insider_recent":[],"earnings_history":[{"period":"2025-06-30","report_date":"2025-08-15","actual":-6.09,"estimate":0.0,"surprise_pct":null,"timing":null},{"period":"2024-12-31","report_date":"2025-02-12","actual":-6.58,"estimate":0.0,"surprise_pct":null,"timing":null}],"next_earnings":null,"splits_divs":{"splits":[],"dividends":[]}}