{"base":{"symbol":"PBOT.US","name":"Pictet AI & Automation ETF","exchange":"NYSE","exchange_name":null,"country":"USA","region":"US","currency":"USD","status":"priced","list_date":"2025-10-16","filing_date":"2025-10-16","amended_date":"2025-10-16","deal_type":"Expected","offer_price":null,"price_low":null,"price_high":null,"shares":null,"last_price":null,"previous_close":null,"change_pct":null,"sector":null,"industry":null,"description":"The fund is an actively managed exchange-traded fund (\"ETF\") that seeks to achieve its investment objective by investing, under normal market conditions, at least 80% of its net assets (plus borrowings for investment purposes) in global eq…","market_cap":null,"employees":null,"web_url":null,"logo_url":null,"tags":["USA","Priced"],"prospectus_url":null},"stats":[{"label":"Symbol","value":"PBOT.US"},{"label":"Country","value":"USA"},{"label":"Beta","value":"0.00"},{"label":"52W High","value":"$29.24"},{"label":"52W Low","value":"$22.52"},{"label":"IPO Date","value":"2025-10-16"}],"financials":{"rows":[],"fiscal_year_end":null,"reporting_currency":null},"analyst":{"rating":null,"target_price":null,"target_pct_vs_current":null,"strong_buy":0,"buy":0,"hold":0,"sell":0,"strong_sell":0},"top_holders":[],"insider_recent":[],"earnings_history":[],"next_earnings":null,"splits_divs":{"splits":[],"dividends":[]}}