{"base":{"symbol":"POM.US","name":"POMDOCTOR LIMITED American Depositary Shares","exchange":"NASDAQ","exchange_name":null,"country":"USA","region":"US","currency":"USD","status":"priced","list_date":"2025-10-08","filing_date":"2025-10-08","amended_date":"2025-10-08","deal_type":"Priced","offer_price":null,"price_low":null,"price_high":null,"shares":5000004,"last_price":null,"previous_close":null,"change_pct":null,"sector":"Healthcare","industry":"Pharmaceutical Retailers","description":"Pomdoctor Limited, through its subsidiaries, offers an online B2C portal to sell pharmaceutical products.","market_cap":14238043.0,"employees":156,"web_url":"https://www.7lk.com","logo_url":null,"tags":["Healthcare","Pharmaceutical Retailers","Nano-cap","USA","Priced"],"prospectus_url":null},"stats":[{"label":"Symbol","value":"POM.US"},{"label":"Sector","value":"Healthcare"},{"label":"Industry","value":"Pharmaceutical Retailers"},{"label":"Country","value":"USA"},{"label":"Employees","value":"156"},{"label":"Market Cap","value":"$14.24M"},{"label":"Revenue (TTM)","value":"$399.91M"},{"label":"EBITDA","value":"$-116.38M"},{"label":"Profit Margin","value":"-53.16%"},{"label":"ROE (TTM)","value":"0.00%"},{"label":"Forward P/E","value":"0.00"},{"label":"52W High","value":"$6.43"},{"label":"52W Low","value":"$0.07"},{"label":"IPO Date","value":"2025-10-08"},{"label":"Fiscal Year End","value":"December"}],"financials":{"rows":[{"label":"Revenue","period_labels":["2022","2023","2024","2025"],"values":["¥245.22M","¥304.85M","¥342.56M","¥399.91M"]},{"label":"Net Income","period_labels":["2022","2023","2024","2025"],"values":["¥-125.51M","¥-145.39M","¥-143.36M","¥-212.58M"]},{"label":"EBITDA","period_labels":["2022","2023","2024","2025"],"values":["¥-3.81M","¥-22.99M","¥-24.27M","—"]},{"label":"Operating Cash Flow","period_labels":["2022","2023","2024","2025"],"values":["¥-22.02M","¥-45.80M","¥-16.13M","¥-148.48M"]},{"label":"Total Assets","period_labels":["2022","2023","2024","2025"],"values":["¥48.62M","¥66.31M","¥46.23M","¥107.56M"]},{"label":"Total Equity","period_labels":["2022","2023","2024","2025"],"values":["¥-1.97B","¥-2.12B","¥-2.26B","¥-453.97M"]},{"label":"Net Margin","period_labels":["2022","2023","2024","2025"],"values":["-51.18%","-47.69%","-41.85%","-53.16%"]}],"fiscal_year_end":"December","reporting_currency":"CNY"},"analyst":{"rating":null,"target_price":null,"target_pct_vs_current":null,"strong_buy":0,"buy":0,"hold":0,"sell":0,"strong_sell":0},"top_holders":[{"rank":1,"name":"XTX Topco Ltd","pct":0.3099,"change_pct":0.0,"date":"2025-12-31"},{"rank":2,"name":"Susquehanna International Group, LLP","pct":0.0496,"change_pct":0.0,"date":"2026-03-31"},{"rank":3,"name":"HRT FINANCIAL LLC","pct":0.0488,"change_pct":0.0,"date":"2025-12-31"},{"rank":4,"name":"Caitong International Asset Management Co., Limited.","pct":0.031,"change_pct":0.0,"date":"2025-12-31"},{"rank":5,"name":"Scientech Research LLC","pct":0.0144,"change_pct":0.0,"date":"2025-12-31"},{"rank":6,"name":"UBS Group AG","pct":0.014,"change_pct":-92.478,"date":"2026-03-31"},{"rank":7,"name":"Ground Swell Capital, LLC","pct":0.0097,"change_pct":0.0,"date":"2026-03-31"},{"rank":8,"name":"StoneX Group Inc","pct":0.0085,"change_pct":0.0,"date":"2025-12-31"},{"rank":9,"name":"Rhumbline Advisers","pct":0.0006,"change_pct":0.0,"date":"2026-03-31"},{"rank":10,"name":"Millennium Management LLC","pct":0.0,"change_pct":-100.0,"date":"2026-03-31"}],"insider_recent":[],"earnings_history":[{"period":"2025-09-30","report_date":"2025-12-03","actual":-1.91,"estimate":0.0,"surprise_pct":null,"timing":null},{"period":"2024-12-31","report_date":"2025-03-31","actual":-1.49,"estimate":0.0,"surprise_pct":null,"timing":null}],"next_earnings":null,"splits_divs":{"splits":[],"dividends":[]}}