[{"date":"2025-09-04T12:55:00+00:00","title":"NYSE Content Advisory: Pre-Market Update + Biotech Enveda raises $150 million to reach unicorn status","content":"NEW YORK, Sept. 4, 2025 /CNW/ -- The New York Stock Exchange (NYSE) provides a daily pre-market update directly from the NYSE Trading Floor. Access today's NYSE Pre-market update for market insights before trading begins.\n\nKristen Scholer delivers the pre-market update on September 4th\n\nStocks are fractionally higher Thursday morning after the S&P 500 rose about half a percentage point on Wednesday. Gains in shares of Big Tech including Alphabet and Apple fueled the rise. A read of private sector payrolls today is expected to show 75,000 jobs were added last month. It precedes the non-farm payrolls report on Friday. Economists anticipate unemployment ticked higher in August to 4.3%. Private Biotech firm Enveda announced its reached unicorn status. The clinical stage company is looking at a valuation of more than a billion dollars after closing its latest round of funding.\n\nOpening Bell Vontobel Asset Management celebrates its entry into the active ETF market with the launch of the Vontobel International Equity Active ETF (NYSE: VNIE)\n\nClosing Bell Fast Company celebrates the 30th anniversary of the Fast Company Innovation Festival\n\nClick here to download the NYSE TV AppNYSE Logo (PRNewsfoto/New York Stock Exchange)Cision\n\nView original content to download multimedia:https://www.prnewswire.com/news-releases/nyse-content-advisory-pre-market-update--biotech-enveda-raises-150-million-to-reach-unicorn-status-302546559.html\n\nSOURCE New York Stock ExchangeCision\n\nView original content to download multimedia: http://www.newswire.ca/en/releases/archive/September2025/04/c1013.html\n\nView Comments","link":"https://finance.yahoo.com/news/nyse-content-advisory-pre-market-125500749.html","symbols":["1AAPL.MI","1GOOG.MI","1GOOGL.MI","AAPL.BA","AAPL.MX","AAPL.US","AAPL34.SA","ABE0.F","ABEA.F","ABEC.F","APC.BE","APC.DU","APC.F","APC.HA","APC.HM","APC.MU","APC8.F","GOGL34.SA","GOGL35.SA","GOOG.MX","GOOG.US","GOOGL.BA","GOOGL.MX","GOOGL.SN","GOOGL.US","I1CE34.SA","IC2.F","ICE.US","SPX.INDX","VNIE.US"],"tags":["ACTIVE ETF MARKET","NEW YORK STOCK EXCHANGE","NON-FARM PAYROLLS","NYSE TRADING FLOOR","PRIVATE SECTOR PAYROLLS","S&P 500"],"sentiment":{"polarity":0.972,"neg":0.025,"neu":0.837,"pos":0.138}}]